protosearch/__init__.py
protosearch/active_learning/active_learning.py
protosearch/active_learning/analyse.py
protosearch/build_bulk/Wyckoff.dat
protosearch/build_bulk/__init__.py
protosearch/build_bulk/build_bulk.py
protosearch/build_bulk/cell_parameters.py
protosearch/build_bulk/classification.py
protosearch/build_bulk/coordination_environment.py
protosearch/build_bulk/enumeration.py
protosearch/build_bulk/fitness_function.py
protosearch/build_bulk/oqmd_icsd.db
protosearch/build_bulk/oqmd_interface.py
protosearch/build_bulk/spglib_interface.py
protosearch/build_bulk/wyckoff_symmetries.py
protosearch/build_bulk/tests/test_build_bulk.py
protosearch/build_bulk/tests/test_cell_parameters.py
protosearch/build_bulk/tests/test_classification.py
protosearch/build_bulk/tests/test_enumerator.py
protosearch/build_bulk/tests/test_oqmd.py
protosearch/build_bulk/tests/test_spacegroups.py
protosearch/calculate/calculator.py
protosearch/calculate/dummy_calc.py
protosearch/calculate/submit.py
protosearch/calculate/vasp.py
protosearch/calculate/tests/test_submit.py
protosearch/calculate/tests/write_model.py
protosearch/enumeration/enumeration.py
protosearch/enumeration/enumeration2.py
protosearch/examples/build.py
protosearch/ml_modelling/fingerprint.py
protosearch/ml_modelling/regression_model.py
protosearch/oqmd/AB2_unique.csv
protosearch/oqmd/prototype_structures.py
protosearch/utils/__init__.py
protosearch/utils/data.py
protosearch/utils/standards.py
protosearch/utils/valence.py
protosearch/workflow/__init__.py
protosearch/workflow/acqusition.py
protosearch/workflow/convergence.py
protosearch/workflow/m_l_interface.py
protosearch/workflow/prototype_db.py
protosearch/workflow/standard_states.py
protosearch/workflow/workflow.py
protosearch/workflow/tests/workflow_submit.py
protosearch-2020.5.10.dist-info/LICENSE
protosearch-2020.5.10.dist-info/METADATA
protosearch-2020.5.10.dist-info/WHEEL
protosearch-2020.5.10.dist-info/top_level.txt
protosearch-2020.5.10.dist-info/RECORD
