Metadata-Version: 2.1
Name: protosearch
Version: 2020.5.10
Summary: Software for enumerating crystal structure prototypes to by used for active learning exploration with DFT and machine learning.
Home-page: https://github.com/ToyotaReseachInstitute/protosearch
Author: Kirsten Winther, SUNCAT-Center, TRI-AMDD
Author-email: 
Maintainer: Kirsten Winther
Maintainer-email: 
License: Apache
Keywords: materials,chemistry,science,crystal,density functional theory,energy,AI,artificial intelligence,sequential learning,active learning
Platform: UNKNOWN
Classifier: Programming Language :: Python :: 3
Classifier: License :: OSI Approved :: Apache Software License
Classifier: Operating System :: OS Independent
Requires-Dist: ase (>=3.19)
Requires-Dist: numpy (>=1.18)
Requires-Dist: CatLearn (>=0.6.2)
Requires-Dist: shapely
Provides-Extra: enumerator
Requires-Dist: BulkEnumerator (>=0.0.2) ; extra == 'enumerator'
